{
	"ABI version": 2,
	"version": "2.1",
	"header": ["time", "expire"],
	"functions": [
		{
			"name": "constructor",
			"inputs": [
			],
			"outputs": [
			]
		},
		{
			"name": "add",
			"inputs": [
				{"name":"title","type":"string"}
			],
			"outputs": [
				{"name":"value0","type":"uint8"}
			]
		},
		{
			"name": "countOpenTasks",
			"inputs": [
			],
			"outputs": [
				{"name":"value0","type":"uint8"}
			]
		},
		{
			"name": "getList",
			"inputs": [
			],
			"outputs": [
				{"name":"value0","type":"string"}
			]
		},
		{
			"name": "getTask",
			"inputs": [
				{"name":"i","type":"uint8"}
			],
			"outputs": [
				{"components":[{"name":"title","type":"string"},{"name":"timestamp","type":"uint32"},{"name":"done","type":"bool"}],"name":"value0","type":"tuple"}
			]
		},
		{
			"name": "deleteTask",
			"inputs": [
				{"name":"i","type":"uint8"}
			],
			"outputs": [
				{"name":"value0","type":"string"}
			]
		},
		{
			"name": "doneTask",
			"inputs": [
				{"name":"i","type":"uint8"}
			],
			"outputs": [
				{"name":"value0","type":"string"}
			]
		},
		{
			"name": "num",
			"inputs": [
			],
			"outputs": [
				{"name":"num","type":"uint8"}
			]
		}
	],
	"data": [
	],
	"events": [
	],
	"fields": [
		{"name":"_pubkey","type":"uint256"},
		{"name":"_timestamp","type":"uint64"},
		{"name":"_constructorFlag","type":"bool"},
		{"components":[{"name":"title","type":"string"},{"name":"timestamp","type":"uint32"},{"name":"done","type":"bool"}],"name":"tasks_array","type":"map(uint8,tuple)"},
		{"name":"num","type":"uint8"}
	]
}
